README.md
setup.py
best_dev_utilllll/__init__.py
best_dev_utilllll/dev_tools.py
best_dev_utilllll/sys_info.py
best_dev_utilllll.egg-info/PKG-INFO
best_dev_utilllll.egg-info/SOURCES.txt
best_dev_utilllll.egg-info/dependency_links.txt
best_dev_utilllll.egg-info/requires.txt
best_dev_utilllll.egg-info/top_level.txt
best_dev_utilllll/utils/__init__.py
best_dev_utilllll/utils/helpers.py