Metadata-Version: 2.1
Name: best-dev-utilllll
Version: 0.1.0
Summary: A package with useful utilities for Python developers 2 .
Author: John Stephans
Author-email: bchsjbcsabcja131312cjbsacsc@gmail.com
Keywords: utils,development,system,network,files
Classifier: Development Status :: 3 - Alpha
Classifier: Intended Audience :: Developers
Classifier: License :: OSI Approved :: MIT License
Classifier: Operating System :: OS Independent
Classifier: Programming Language :: Python :: 3
Classifier: Programming Language :: Python :: 3.7
Classifier: Programming Language :: Python :: 3.8
Classifier: Programming Language :: Python :: 3.9
Classifier: Programming Language :: Python :: 3.10
Classifier: Programming Language :: Python :: 3.11
Requires-Python: >=3.7
